LICENSE.txt
MANIFEST.in
README.md
setup.py
Topsis_Ayush_1020161/__init__.py
Topsis_Ayush_1020161/topsis.py
Topsis_Ayush_1020161.egg-info/PKG-INFO
Topsis_Ayush_1020161.egg-info/SOURCES.txt
Topsis_Ayush_1020161.egg-info/dependency_links.txt
Topsis_Ayush_1020161.egg-info/requires.txt
Topsis_Ayush_1020161.egg-info/top_level.txt